<class id="SEGuardian" cpp_class="CVXHero" parent="Captain" entity="Units/EGuardian/EGuardian.ent.xml">

	<properties race="Egypt"/>
	<properties maxhealth="2000"/>
	<properties damage="30" armor_slash="8" armor_pierce="8"/>
	<properties speed="80"/>
	<properties unit_specials="Deflection, Active, Ferocity"/>
	<properties interface="thumb,unit,items"/>
	<properties HeroSkills="Team attack, Team defense, Quick March, Survival, Recovery, Vigor, Wisdom, Epic attack, Epic armor, Epic endurance"/>
	<properties icon="gameres/icons/EGUARDIANGUARD.bmp"/>
	<properties display_name="Guardian" display_name_plural="Guardians"/>
	<properties help="contents/units/EGuardian"/>
	<properties edittree_pos="Units/Special Heroes/Guardian"/>
	<sounds command="data/sound entities/VoiceEGuardian.xml"/>
	<properties max_army="100"/>
	<properties inventory_size="8"/>	
	<method sig="toHero" vs="data/subai/hero_convert.vs"/>

</class>
